[
  {
    "pin": 25,
    "active": true,
    "name": "HLT",
    "type": {
      "controller": "PID",
      "config": {
        "set_point": 212,
        "mode": 0,
        "output": 60
      }
    },
    "input": "HLT",
    "mode": "TPC",
    "log": "log"
  },
  {
    "id": 1,
    "pin": 8,
    "active": true,
    "name": "BK",
    "type": {
      "controller": "PID",
      "config": {
        "set_point": 70,
        "mode": 1,
        "kp": 25,
        "ki": 5,
        "kd": 5
      }
    },
    "input": "BK2",
    "mode": "TPC",
    "log": "log"
  }
]